virtualenv_tauthon/__init__.py
virtualenv_tauthon/create.py
virtualenv_tauthon-0.0.2.dist-info/LICENSE
virtualenv_tauthon-0.0.2.dist-info/METADATA
virtualenv_tauthon-0.0.2.dist-info/WHEEL
virtualenv_tauthon-0.0.2.dist-info/entry_points.txt
virtualenv_tauthon-0.0.2.dist-info/top_level.txt
virtualenv_tauthon-0.0.2.dist-info/RECORD
